PyMIPS/__init__.py
PyMIPS/__main__.py
PyMIPS/lexer.py
PyMIPS/AST/__init__.py
PyMIPS/AST/ast.py
PyMIPS/AST/ast_utils.py
PyMIPS/AST/blocks.py
PyMIPS/AST/combinators.py
PyMIPS/AST/data.py
PyMIPS/AST/validator.py
PyMIPS/AST/Parsers/__init__.py
PyMIPS/AST/Parsers/data.py
PyMIPS/AST/Parsers/text.py
PyMIPS/Datastructure/__init__.py
PyMIPS/Datastructure/commands.py
PyMIPS/Datastructure/data_commands.py
PyMIPS/Datastructure/data_model.py
PyMIPS/Datastructure/execution_stack.py
PyMIPS/Datastructure/instruction_types.py
PyMIPS/Datastructure/math_utils.py
PyMIPS/Datastructure/memory.py
PyMIPS/tests/__init__.py
PyMIPS/tests/data_model_test.py
PyMIPS/tests/example1_test.py
PyMIPS/tests/memory_test.py
PyMIPS/tests/register_test.py
PyMIPS/tests/test_commands.py
PyMIPS/tests/validator_test.py
PyMIPS-1.0.0.dist-info/LICENSE
PyMIPS-1.0.0.dist-info/METADATA
PyMIPS-1.0.0.dist-info/WHEEL
PyMIPS-1.0.0.dist-info/entry_points.txt
PyMIPS-1.0.0.dist-info/top_level.txt
PyMIPS-1.0.0.dist-info/RECORD
