Metadata-Version: 2.1
Name: PyMIPS
Version: 1.0.0
Summary: A python MIPS interpreter
Home-page: https://github.com/AshtonUPS/Py-MI-PS
Author: Ashton Walden & Jiman Kim
Author-email: awalden@pugetsound.edu
License: MIT
Platform: UNKNOWN
